{"cameraMode":{"drawMode":0,"name":"Shaded","section":"Shading Mode"},"sceneLighting":true,"audioPlay":false,"sceneViewState":{"m_AlwaysRefresh":false,"showFog":true,"showSkybox":true,"showFlares":true,"showImageEffects":true,"showParticleSystems":true,"showVisualEffectGraphs":true,"m_FxEnabled":true},"in2DMode":false,"pivot":{"x":-10.125763893127442,"y":-10.526361465454102,"z":13.781065940856934},"rotation":{"x":-0.47714513540267947,"y":0.0005224550259299576,"z":-0.00027978760772384703,"w":-0.8788337111473084},"size":28.20064353942871,"orthographic":false}